{
	"id": "gr-7-e50",
	"name": "GR 7 E50 CASTALLA - ELDA",
	"type": "GR",
	"status": "homologado",
	"status_detail": "Control de calidad positivo",
	"municipality": "Castalla",
	"zone": "alcoia",
	"aemet_municipio": null,
	"start": {
		"lat": 38.60656002536416,
		"lon": -0.668674036860466,
		"name": "Cruce Av. Holanda con Av. Ibi. Castalla"
	},
	"distance_km": 24,
	"ascent_m": 445,
	"descent_m": 715,
	"circular": false,
	"difficulty_mide": {
		"medio": 2,
		"itinerario": 2,
		"desplazamiento": 1,
		"esfuerzo": 4
	},
	"est_duration_min": 430,
	"water_points": [],
	"escape_routes": [],
	"highlights": [],
	"best_season": [],
	"best_start_time": null,
	"shade_ratio": null,
	"gpx": "gr-7-e50.gpx",
	"links": {
		"femecv": "https://senders.femecv.com/es/sendero/ver/gr-7-e50",
		"wikiloc": null
	},
	"alternatives": [],
	"notes_rain": null,
	"bbox": [
		-0.801647985354066,
		38.47519498318434,
		-0.665941033512354,
		38.60656002536416
	],
	"sources": [
		"Ficha FEMECV https://senders.femecv.com/es/sendero/ver/gr-7-e50 (crawl 2026-06-11): nombre, estado \"Control de calidad positivo\", distancia, desniveles, horario teórico, MIDE, modalidad, municipio, comarca",
		"GPX gr-7-e50.gpx (derivados: inicio, bbox)"
	]
}
