{
	"id": "pr-cv-195",
	"name": "PR-CV 195 LAS CAÑADAS",
	"type": "PR",
	"status": "con_reservas",
	"status_detail": "Control de calidad condicionado",
	"municipality": "Elda",
	"zone": "vinalopo-mitja",
	"aemet_municipio": null,
	"start": {
		"lat": 38.47516296431422,
		"lon": -0.801610015332699,
		"name": "Jardines del Vinalopó. Elda"
	},
	"end": {
		"lat": 38.4751639701426,
		"lon": -0.801615966483951
	},
	"distance_km": 11.9,
	"ascent_m": 190,
	"descent_m": 190,
	"circular": true,
	"difficulty_mide": {
		"medio": 1,
		"itinerario": 2,
		"desplazamiento": 2,
		"esfuerzo": 3
	},
	"est_duration_min": 205,
	"water_points": [],
	"water_points_geo": [],
	"pois": [
		{
			"name": "Pórtico del Cementerio",
			"type": "patrimonio",
			"lat": 38.4660877,
			"lon": -0.8288863,
			"km": 8.7,
			"dist_m": 61
		}
	],
	"escape_routes": [],
	"highlights": [],
	"best_season": [],
	"best_start_time": null,
	"shade_ratio": 0.05,
	"gpx": "pr-cv-195.gpx",
	"links": {
		"femecv": "https://senders.femecv.com/es/sendero/ver/pr-cv-195",
		"wikiloc": null
	},
	"alternatives": [
		"gr-7-e51",
		"pr-cv-196",
		"pr-cv-221"
	],
	"notes_rain": null,
	"bbox": [
		-0.849450984969735,
		38.46381202340126,
		-0.801537008956075,
		38.48935696296394
	],
	"sources": [
		"Ficha FEMECV https://senders.femecv.com/es/sendero/ver/pr-cv-195 (crawl 2026-06-11): nombre, estado \"Control de calidad condicionado\", distancia, desniveles, horario teórico, MIDE, modalidad, municipio, comarca",
		"OSM Overpass (enrich 2026-06-20): fuentes de agua, sombra estimada y alternativas por proximidad — no verificado en campo",
		"GPX pr-cv-195.gpx (derivados: inicio, bbox)"
	],
	"federacion": "FEMECV",
	"comunidad": "Comunitat Valenciana",
	"capabilities": {
		"estado": true,
		"mide": true,
		"agua": true,
		"etapas": true,
		"descripcion": true,
		"fauna": true,
		"escapes": true
	}
}
