{
	"id": "pr-cv-135",
	"name": "PR-CV 135 FONT JORDANA (AGULLENT) - FONT DE TARRAGÓ (ALFAFARA)",
	"type": "PR",
	"status": "homologado",
	"status_detail": "Control de calidad positivo",
	"municipality": "Agullent",
	"zone": "vall-d-albaida",
	"aemet_municipio": null,
	"start": {
		"lat": 38.81977804005146,
		"lon": -0.549293020740151,
		"name": "Font Jordana. Agullent"
	},
	"distance_km": 10.7,
	"ascent_m": 460,
	"descent_m": 230,
	"circular": false,
	"difficulty_mide": {
		"medio": 2,
		"itinerario": 2,
		"desplazamiento": 1,
		"esfuerzo": 2
	},
	"est_duration_min": 205,
	"water_points": [
		"Manantial \"Font Jordana\" (km 0.1, a 35 m del track; OSM, no verificado en campo)"
	],
	"water_points_geo": [
		{
			"name": "Font Jordana",
			"kind": "manantial",
			"lat": 38.8192897,
			"lon": -0.5487679,
			"km": 0.1,
			"dist_m": 35
		}
	],
	"pois": [
		{
			"name": "Alt del Torrater",
			"type": "cumbre",
			"lat": 38.8029315,
			"lon": -0.5646296,
			"km": 3.4,
			"dist_m": 81
		}
	],
	"escape_routes": [],
	"highlights": [],
	"best_season": [],
	"best_start_time": null,
	"shade_ratio": 0.03,
	"gpx": "pr-cv-135.gpx",
	"links": {
		"femecv": "https://senders.femecv.com/es/sendero/ver/pr-cv-135",
		"wikiloc": null
	},
	"alternatives": [
		"pr-cv-134",
		"pr-cv-222",
		"sl-cv-118"
	],
	"notes_rain": null,
	"bbox": [
		-0.56381399743259,
		38.767014965415,
		-0.548247965052724,
		38.81977804005146
	],
	"sources": [
		"Ficha FEMECV https://senders.femecv.com/es/sendero/ver/pr-cv-135 (crawl 2026-06-11): nombre, estado \"Control de calidad positivo\", distancia, desniveles, horario teórico, MIDE, modalidad, municipio, comarca",
		"OSM Overpass (enrich 2026-06-20): fuentes de agua, sombra estimada y alternativas por proximidad — no verificado en campo",
		"GPX pr-cv-135.gpx (derivados: inicio, bbox)"
	]
}
