{
	"id": "sl-cv-102",
	"name": "SL-CV 102 BARRANC DE LA FRESCA",
	"type": "SL",
	"status": "homologado",
	"status_detail": "Control de calidad positivo",
	"municipality": "Benassal",
	"zone": "alt-maestrat",
	"aemet_municipio": null,
	"start": {
		"lat": 40.381698,
		"lon": -0.140335,
		"name": "Calle Ares, 20. Benasal"
	},
	"distance_km": 9.2,
	"ascent_m": 230,
	"descent_m": 230,
	"circular": true,
	"difficulty_mide": {
		"medio": 1,
		"itinerario": 2,
		"desplazamiento": 2,
		"esfuerzo": 2
	},
	"est_duration_min": 165,
	"water_points": [],
	"water_points_geo": [],
	"pois": [],
	"escape_routes": [],
	"highlights": [],
	"best_season": [],
	"best_start_time": null,
	"shade_ratio": null,
	"gpx": "sl-cv-102.gpx",
	"links": {
		"femecv": "https://senders.femecv.com/es/sendero/ver/sl-cv-102",
		"wikiloc": null
	},
	"alternatives": [],
	"notes_rain": null,
	"bbox": [
		-0.141206,
		40.378031,
		-0.114343,
		40.40399
	],
	"sources": [
		"Ficha FEMECV https://senders.femecv.com/es/sendero/ver/sl-cv-102 (crawl 2026-06-11): nombre, estado \"Control de calidad positivo\", distancia, desniveles, horario teórico, MIDE, modalidad, municipio, comarca",
		"GPX sl-cv-102.gpx (derivados: inicio, bbox)"
	]
}
