{
	"name": "GR 37 E05 LA TORRE - ARAS DE LOS OLMOS",
	"type": "GR",
	"status": "con_reservas",
	"status_detail": "Control de calidad condicionado",
	"municipality": "Alpuente",
	"comarca": "Los Serranos",
	"distance_km": 16.6,
	"ascent_m": 400,
	"descent_m": 665,
	"circular": false,
	"difficulty_mide": {
		"medio": 2,
		"itinerario": 2,
		"desplazamiento": 2,
		"esfuerzo": 3
	},
	"est_duration_min": 310,
	"start_name": "La Torre. Alpuente",
	"femecv_url": "https://senders.femecv.com/es/sendero/ver/gr-37-e05",
	"gpx_url": "https://femecv.blob.core.windows.net/publico/gpx/3d4fb0418bTRACKGR037E05.gpx",
	"crawled_at": "2026-06-11T13:58:58.991Z"
}
