{
	"name": "PR-CV 53 SENDERO DE PEDREGUER",
	"type": "PR",
	"status": "con_reservas",
	"status_detail": "Sin controles de calidad",
	"municipality": "Pedreguer",
	"comarca": "La Marina Alta",
	"distance_km": 19.1,
	"ascent_m": 1120,
	"descent_m": 1120,
	"circular": true,
	"difficulty_mide": {
		"medio": 1,
		"itinerario": 2,
		"desplazamiento": 2,
		"esfuerzo": 4
	},
	"est_duration_min": 425,
	"start_name": "Parc del Patronat. Pedreguer",
	"femecv_url": "https://senders.femecv.com/es/sendero/ver/pr-cv-53",
	"gpx_url": "https://femecv.blob.core.windows.net/publico/gpx/TRACKPRCV053.gpx",
	"crawled_at": "2026-06-11T14:12:14.842Z"
}
