{
	"name": "PR-CV 399 LA ROMANA - PEÑA LA MINA - ALGAYAT",
	"type": "PR",
	"status": "con_reservas",
	"status_detail": "Sin controles de calidad",
	"municipality": "Romana (La)",
	"comarca": "Vinalopò Mitja",
	"distance_km": 13.25,
	"ascent_m": null,
	"descent_m": null,
	"circular": false,
	"difficulty_mide": null,
	"est_duration_min": 255,
	"start_name": "La Romana",
	"femecv_url": "https://senders.femecv.com/es/sendero/ver/pr-cv-399",
	"gpx_url": "https://femecv.blob.core.windows.net/publico/gpx/TRACKPRCV399.gpx",
	"crawled_at": "2026-06-11T14:09:33.079Z"
}
