{
	"name": "SL-CV 42 SENDA DELS LLADRES",
	"type": "SL",
	"status": "con_reservas",
	"status_detail": "Sin controles de calidad",
	"municipality": "Sagunt/Sagunto",
	"comarca": "El Camp de Morvedre",
	"distance_km": 2.4,
	"ascent_m": 120,
	"descent_m": 120,
	"circular": true,
	"difficulty_mide": {
		"medio": 2,
		"itinerario": 2,
		"desplazamiento": 3,
		"esfuerzo": 1
	},
	"est_duration_min": 50,
	"start_name": "C. Castillo. Sagunto",
	"femecv_url": "https://senders.femecv.com/es/sendero/ver/sl-cv-42",
	"gpx_url": "https://femecv.blob.core.windows.net/publico/gpx/TRACKSLCV042.gpx",
	"crawled_at": "2026-06-11T14:17:34.834Z"
}
