{
	"name": "SL-CV 73 SENDA BARRANCO DE XURRA",
	"type": "SL",
	"status": "homologado",
	"status_detail": "Control de calidad positivo",
	"municipality": "Teulada",
	"comarca": "La Marina Alta",
	"distance_km": 1.9,
	"ascent_m": 10,
	"descent_m": 75,
	"circular": false,
	"difficulty_mide": {
		"medio": 2,
		"itinerario": 2,
		"desplazamiento": 2,
		"esfuerzo": 1
	},
	"est_duration_min": 35,
	"start_name": "Avda. del Mediterráneo, esquina con calle Médico José Pitarch. Teulada",
	"femecv_url": "https://senders.femecv.com/es/sendero/ver/sl-cv-73",
	"gpx_url": "https://femecv.blob.core.windows.net/publico/gpx/TRACKSLCV073.gpx",
	"crawled_at": "2026-06-11T14:18:36.693Z"
}
