{
	"name": "SL-CV 121 VOLTA A AIGÜES",
	"type": "SL",
	"status": "homologado",
	"status_detail": "Control de calidad positivo",
	"municipality": "Aigües",
	"comarca": "L'Alacantí",
	"distance_km": 7.5,
	"ascent_m": 205,
	"descent_m": 205,
	"circular": true,
	"difficulty_mide": {
		"medio": 2,
		"itinerario": 2,
		"desplazamiento": 2,
		"esfuerzo": 2
	},
	"est_duration_min": 140,
	"start_name": "Casa de la Cultura. Aigües",
	"femecv_url": "https://senders.femecv.com/es/sendero/ver/sl-cv-121",
	"gpx_url": "https://femecv.blob.core.windows.net/publico/gpx/9cb39348cbTRACKSLCV121.gpx",
	"crawled_at": "2026-06-11T14:14:22.908Z"
}
