{
	"water_points": [
		"Fuente (km 4.7, a 9 m del track; OSM, no verificado en campo)"
	],
	"water_points_geo": [
		{
			"name": null,
			"kind": "fuente",
			"lat": 42.9888381,
			"lon": -1.1068227,
			"km": 4.7,
			"dist_m": 9
		}
	],
	"pois": [
		{
			"name": "Arrizabala",
			"type": "patrimonio",
			"lat": 42.9567577,
			"lon": -1.1024795,
			"km": 0,
			"dist_m": 61
		},
		{
			"name": "Mugarrien 231. zenbakia",
			"type": "patrimonio",
			"lat": 43.0028681,
			"lon": -1.0859632,
			"km": 7.9,
			"dist_m": 29
		},
		{
			"name": "Mugarrien 230. zenbakia",
			"type": "patrimonio",
			"lat": 43.0113231,
			"lon": -1.0837163,
			"km": 9,
			"dist_m": 37
		},
		{
			"name": "Euskal Herriko mugarria",
			"type": "patrimonio",
			"lat": 43.0114471,
			"lon": -1.0835918,
			"km": 9,
			"dist_m": 54
		}
	],
	"shade_ratio": 0,
	"alternatives": [
		"na-gr-t-10",
		"na-gr-t-08"
	],
	"enriched_at": "2026-06-30T14:48:41.732Z",
	"method": "OSM Overpass: fuentes/manantiales a ≤100 m del track (con coordenadas); POIs (mirador/cumbre/patrimonio/refugio) a ≤150 m; sombra = % de puntos del track bajo polígonos natural=wood/landuse=forest (estimación a la baja, multipolígonos omitidos)"
}
